mcp_auto_backup/__init__.py
mcp_auto_backup/cli.py
mcp_auto_backup/server.py
mcp_auto_backup/config/__init__.py
mcp_auto_backup/config/settings.py
mcp_auto_backup/core/__init__.py
mcp_auto_backup/core/backup.py
mcp_auto_backup/core/storage.py
mcp_auto_backup/core/utils.py
mcp_auto_backup/tools/__init__.py
mcp_auto_backup/tools/file_tools.py
mcp_auto_backup/tools/folder_tools.py
mcp_auto_backup-0.1.1.dist-info/METADATA
mcp_auto_backup-0.1.1.dist-info/WHEEL
mcp_auto_backup-0.1.1.dist-info/entry_points.txt
mcp_auto_backup-0.1.1.dist-info/licenses/LICENSE
mcp_auto_backup-0.1.1.dist-info/RECORD
