Metadata-Version: 2.4
Name: mcp-auto-backup
Version: 0.1.1
Summary: A lightweight MCP backup tool for AI Agents - simpler than Git, focused on quick backup needs
Project-URL: Homepage, https://github.com/yourusername/mcp-auto-backup
Project-URL: Repository, https://github.com/yourusername/mcp-auto-backup
Project-URL: Documentation, https://github.com/yourusername/mcp-auto-backup#readme
Project-URL: Bug Tracker, https://github.com/yourusername/mcp-auto-backup/issues
Author-email: MCP Auto Backup Team <mcp-backup@example.com>
License: MIT
License-File: LICENSE
Keywords: null
Classifier: Development Status :: 4 - Beta
Classifier: Intended Audience :: Developers
Classifier: License :: OSI Approved :: MIT License
Classifier: Programming Language :: Python :: 3
Classifier: Programming Language :: Python :: 3.10
Classifier: Programming Language :: Python :: 3.11
Classifier: Programming Language :: Python :: 3.12
Classifier: Topic :: Software Development :: Libraries :: Python Modules
Classifier: Topic :: System :: Archiving :: Backup
Requires-Python: >=3.10
Requires-Dist: aiofiles>=23.0.0
Requires-Dist: click>=8.0.0
Requires-Dist: cryptography>=41.0.0
Requires-Dist: mcp>=1.0.0
Requires-Dist: pydantic-settings>=2.0.0
Requires-Dist: pydantic>=2.0.0
Requires-Dist: uvicorn>=0.24.0
Provides-Extra: cli
Requires-Dist: rich>=13.0.0; extra == 'cli'
Requires-Dist: typer>=0.9.0; extra == 'cli'
Provides-Extra: dev
Requires-Dist: black>=23.0.0; extra == 'dev'
Requires-Dist: mypy>=1.0.0; extra == 'dev'
Requires-Dist: pre-commit>=3.0.0; extra == 'dev'
Requires-Dist: pytest-asyncio>=0.21.0; extra == 'dev'
Requires-Dist: pytest-cov>=4.0.0; extra == 'dev'
Requires-Dist: pytest>=7.0.0; extra == 'dev'
Requires-Dist: ruff>=0.1.0; extra == 'dev'
Requires-Dist: twine>=4.0.0; extra == 'dev'
